RPi.DHT-0.5.0.data/scripts/raspi-dht
raspi_dht/__init__.py
raspi_dht/dht.py
raspi_dht/main.py
RPi.DHT-0.5.0.dist-info/LICENSE
RPi.DHT-0.5.0.dist-info/METADATA
RPi.DHT-0.5.0.dist-info/WHEEL
RPi.DHT-0.5.0.dist-info/top_level.txt
RPi.DHT-0.5.0.dist-info/RECORD
