Metadata-Version: 2.1
Name: RPi.DHT
Version: 0.5.0
Summary: Python implementation for Adafruit_DHT sensor for Raspberry Pi.
Home-page: https://github.com/ricco386/RPi.DHT
Author: Richard von Kellner
Author-email: richard.kellner@gmail.com
License: MIT
Platform: UNKNOWN
Classifier: Environment :: Console
Classifier: Intended Audience :: System Administrators
Classifier: Intended Audience :: Developers
Classifier: Intended Audience :: End Users/Desktop
Classifier: Operating System :: Unix
Classifier: Operating System :: POSIX :: Linux
Classifier: License :: OSI Approved :: MIT License
Classifier: Programming Language :: Python
Classifier: Programming Language :: Python :: 3
Classifier: Development Status :: 4 - Beta
Classifier: Topic :: Utilities
Classifier: Topic :: Home Automation
Classifier: Topic :: System :: Hardware
Classifier: Topic :: Terminals
Requires-Dist: Adafruit-Python-DHT
Requires-Dist: RPi.Sensor (>=0.5.3)
